# pydisasm version 3.4.0
# Python bytecode 3.4 (3310)
# Disassembled from Python 3.4.2 (default, May  4 2015, 09:07:28)
# [GCC 4.8.2]
# Timestamp in code: 2017-06-28 14:11:59
# Source code size mod 2**32: 80 bytes
# Method Name:       <module>
# Filename:          exec
# Argument count:    0
# Kw-only arguments: 0
# Number of locals:  0
# Stack size:        2
# Flags:             0x00000040 (NOFREE)
# Constants:
#    0: 1
#    1: 2
#    2: 'nope'
#    3: 'done'
#    4: None
# Names:
#    0: x
#    1: y
#    2: print
  2:          0 LOAD_CONST                0 (1)
              3 STORE_NAME                0 (x)

  3:          6 LOAD_NAME                 0 (x)
              9 LOAD_CONST                1 (2)
             12 BINARY_MULTIPLY
             13 STORE_NAME                1 (y)

  4:         16 LOAD_NAME                 1 (y)
             19 LOAD_CONST                1 (2)
             22 COMPARE_OP                0 (<)
             25 POP_JUMP_IF_FALSE        41 (to 41)

  5:         28 LOAD_NAME                 2 (print)
             31 LOAD_CONST                2 ('nope')
             34 CALL_FUNCTION             1 (1 positional, 0 keyword pair)
             37 POP_TOP
             38 JUMP_FORWARD              0 (to 41)

  6:    >>   41 LOAD_NAME                 2 (print)
             44 LOAD_CONST                3 ('done')
             47 CALL_FUNCTION             1 (1 positional, 0 keyword pair)
             50 POP_TOP
             51 LOAD_CONST                4 (None)
             54 RETURN_VALUE
